rangeKata/__init__.py
rangeKata/kataRange.py
rangeKata/Test/__init__.py
rangeKata/Test/test.py
kataRange-1.0.dist-info/METADATA
kataRange-1.0.dist-info/WHEEL
kataRange-1.0.dist-info/license.txt
kataRange-1.0.dist-info/top_level.txt
kataRange-1.0.dist-info/RECORD
