Metadata-Version: 2.1
Name: kataRange
Version: 1.0
Summary: Range utilities app developed for IDS347L
Home-page: UNKNOWN
Author: Juan Avila & Nathalie Elias
Author-email: avilajuan0301@gmail.com
License: UNKNOWN
Platform: UNKNOWN
Classifier: Programming Language :: Python :: 3
Classifier: License :: OSI Approved :: MIT License
Classifier: Operating System :: OS Independent
